maykin_config_checks/__init__.py
maykin_config_checks/apps.py
maykin_config_checks/py.typed
maykin_config_checks/api/__init__.py
maykin_config_checks/api/views.py
maykin_config_checks/management/__init__.py
maykin_config_checks/management/commands/__init__.py
maykin_config_checks/management/commands/config_checks.py
maykin_config_checks/templates/configuration_health_check.html
maykin_config_checks/templatetags/__init__.py
maykin_config_checks/templatetags/display_health_checks.py
maykin_config_checks-0.1.0.dist-info/licenses/LICENSE
maykin_config_checks-0.1.0.dist-info/METADATA
maykin_config_checks-0.1.0.dist-info/WHEEL
maykin_config_checks-0.1.0.dist-info/top_level.txt
maykin_config_checks-0.1.0.dist-info/RECORD
